<?xml version="1.0" ?>

<container xmlns="http://symfony.com/schema/dic/services"
           xmlns:xsi="http://www.w3.org/2001/XMLSchema-instance"
           xsi:schemaLocation="http://symfony.com/schema/dic/services http://symfony.com/schema/dic/services/services-1.0.xsd">

    <services>
        <service id="app_core.twig.extension.number" class="App\CoreBundle\Twig\Extension\NumberExtension">
            <tag name="twig.extension" alias="app_number" />
        </service>

        <service id="app_core.twig.extension.static" class="App\CoreBundle\Twig\Extension\StaticExtension">
            <argument type="service" id="kernel" />
            <tag name="twig.extension" alias="static" />
        </service>

        <service id="app_core.twig.extension.formatter" class="App\CoreBundle\Twig\Extension\FormatterExtension">
            <argument type="service" id="translator" />
            <tag name="twig.extension" alias="static" />
        </service>
        <service id="app_core.filter.filter" abstract="true">
            <call method="setEntityManager">
                <argument type="service" id="doctrine.orm.entity_manager" />
            </call>
            <call method="setTemplating">
                <argument type="service" id="templating" />
            </call>
            <call method="setContainer">
                <argument type="service" id="service_container" />
            </call>
        </service>
    </services>
</container>
